hostsd/__init__.py
hostsd/__main__.py
hostsd-0.1.4.dist-info/METADATA
hostsd-0.1.4.dist-info/WHEEL
hostsd-0.1.4.dist-info/entry_points.txt
hostsd-0.1.4.dist-info/licenses/LICENSE
hostsd-0.1.4.dist-info/RECORD
