Metadata-Version: 2.4
Name: hostsd
Version: 0.1.4
Summary: A simple hosts file manager
Project-URL: Homepage, https://git.private.coffee/kumi/hostsd
Project-URL: Bug Tracker, https://git.private.coffee/kumi/hostsd/issues
Project-URL: Source Code, https://git.private.coffee/kumi/hostsd
Author-email: Kumi Mitterer <hostsd@kumi.email>
License: Copyright (c) 2023 Kumi Mitterer <hostsd@kumi.email>
License-File: LICENSE
Classifier: License :: OSI Approved :: MIT License
Classifier: Operating System :: OS Independent
Classifier: Programming Language :: Python :: 3
Requires-Python: >=3.8
